[
  {
    "orderID": 10248,
    "customerID": "VINET",
    "employeeID": 5,
    "orderDate": "1996-07-04T00:00:00",
    "requiredDate": "1996-08-01T00:00:00",
    "shippedDate": "1996-07-16T00:00:00",
    "shipVia": 3,
    "freight": 32.3800,
    "shipName": "Vins et alcools Chevalier",
    "shipAddress": "59 rue de l'Abbaye",
    "shipCity": "Reims",
    "shipRegion": null,
    "shipPostalCode": "51100",
    "shipCountry": "France",
    "customer": null,
    "order_Details": []
  },
  {
    "orderID": 10249,
    "customerID": "TOMSP",
    "employeeID": 6,
    "orderDate": "1996-07-05T00:00:00",
    "requiredDate": "1996-08-16T00:00:00",
    "shippedDate": "1996-07-10T00:00:00",
    "shipVia": 1,
    "freight": 11.6100,
    "shipName": "Toms Spezialitäten",
    "shipAddress": "Luisenstr. 48",
    "shipCity": "Münster",
    "shipRegion": null,
    "shipPostalCode": "44087",
    "shipCountry": "Germany",
    "customer": null,
    "order_Details": []
  },
  {
    "orderID": 10250,
    "customerID": "HANAR",
    "employeeID": 4,
    "orderDate": "1996-07-08T00:00:00",
    "requiredDate": "1996-08-05T00:00:00",
    "shippedDate": "1996-07-12T00:00:00",
    "shipVia": 2,
    "freight": 65.8300,
    "shipName": "Hanari Carnes",
    "shipAddress": "Rua do Paço, 67",
    "shipCity": "Rio de Janeiro",
    "shipRegion": "RJ",
    "shipPostalCode": "05454-876",
    "shipCountry": "Brazil",
    "customer": null,
    "order_Details": []
  },
  {
    "orderID": 10251,
    "customerID": "VICTE",
    "employeeID": 3,
    "orderDate": "1996-07-08T00:00:00",
    "requiredDate": "1996-08-05T00:00:00",
    "shippedDate": "1996-07-15T00:00:00",
    "shipVia": 1,
    "freight": 41.3400,
    "shipName": "Victuailles en stock",
    "shipAddress": "2, rue du Commerce",
    "shipCity": "Lyon",
    "shipRegion": null,
    "shipPostalCode": "69004",
    "shipCountry": "France",
    "customer": null,
    "order_Details": []
  }
]